{
  "ProjectID": 1,
  "Name": "Linear algebra ",
  "Packets": [
    {
      "PacketID": 1,
      "Title": "Linear algebra ",
      "Resume": null,
      "Selected": true,
      "Editable": false,
      "ParentID": null,
      "ProjectFK": 1,
      "Project": null,
      "NotePackets": null
    },
    {
      "PacketID": 2,
      "Title": "Fundamentals",
      "Resume": null,
      "Selected": false,
      "Editable": false,
      "ParentID": 1,
      "ProjectFK": 1,
      "Project": null,
      "NotePackets": null
    },
    {
      "PacketID": 3,
      "Title": "Linear Algebra Techniques",
      "Resume": null,
      "Selected": false,
      "Editable": false,
      "ParentID": 1,
      "ProjectFK": 1,
      "Project": null,
      "NotePackets": null
    },
    {
      "PacketID": 4,
      "Title": "Matrices and matrix operations",
      "Resume": null,
      "Selected": false,
      "Editable": false,
      "ParentID": 2,
      "ProjectFK": 1,
      "Project": null,
      "NotePackets": null
    },
    {
      "PacketID": 5,
      "Title": "Vectors and vector operations",
      "Resume": null,
      "Selected": false,
      "Editable": false,
      "ParentID": 2,
      "ProjectFK": 1,
      "Project": null,
      "NotePackets": null
    },
    {
      "PacketID": 6,
      "Title": "Linear combinations and span",
      "Resume": null,
      "Selected": false,
      "Editable": false,
      "ParentID": 2,
      "ProjectFK": 1,
      "Project": null,
      "NotePackets": null
    },
    {
      "PacketID": 7,
      "Title": "Linear independence and rank",
      "Resume": null,
      "Selected": false,
      "Editable": false,
      "ParentID": 2,
      "ProjectFK": 1,
      "Project": null,
      "NotePackets": null
    },
    {
      "PacketID": 8,
      "Title": "Systems of linear equations",
      "Resume": null,
      "Selected": false,
      "Editable": false,
      "ParentID": 2,
      "ProjectFK": 1,
      "Project": null,
      "NotePackets": null
    },
    {
      "PacketID": 9,
      "Title": "Matrix Basics",
      "Resume": null,
      "Selected": false,
      "Editable": false,
      "ParentID": 4,
      "ProjectFK": 1,
      "Project": null,
      "NotePackets": null
    },
    {
      "PacketID": 10,
      "Title": "Matrix Multiplication and Inverse",
      "Resume": null,
      "Selected": false,
      "Editable": false,
      "ParentID": 4,
      "ProjectFK": 1,
      "Project": null,
      "NotePackets": null
    },
    {
      "PacketID": 11,
      "Title": "Matrix Decompositions",
      "Resume": null,
      "Selected": false,
      "Editable": false,
      "ParentID": 4,
      "ProjectFK": 1,
      "Project": null,
      "NotePackets": null
    },
    {
      "PacketID": 12,
      "Title": "Applications of Matrices",
      "Resume": null,
      "Selected": false,
      "Editable": false,
      "ParentID": 4,
      "ProjectFK": 1,
      "Project": null,
      "NotePackets": null
    },
    {
      "PacketID": 13,
      "Title": "Definition of matrices and their elements",
      "Resume": null,
      "Selected": false,
      "Editable": false,
      "ParentID": 9,
      "ProjectFK": 1,
      "Project": null,
      "NotePackets": null
    },
    {
      "PacketID": 14,
      "Title": "Types of matrices (square, rectangular, diagonal, identity, symmetric, etc.)",
      "Resume": null,
      "Selected": false,
      "Editable": false,
      "ParentID": 9,
      "ProjectFK": 1,
      "Project": null,
      "NotePackets": null
    },
    {
      "PacketID": 15,
      "Title": "Matrix addition and subtraction",
      "Resume": null,
      "Selected": false,
      "Editable": false,
      "ParentID": 9,
      "ProjectFK": 1,
      "Project": null,
      "NotePackets": null
    },
    {
      "PacketID": 16,
      "Title": "Scalar multiplication of matrices",
      "Resume": null,
      "Selected": false,
      "Editable": false,
      "ParentID": 9,
      "ProjectFK": 1,
      "Project": null,
      "NotePackets": null
    },
    {
      "PacketID": 17,
      "Title": "Matrix multiplication and its properties",
      "Resume": null,
      "Selected": false,
      "Editable": false,
      "ParentID": 10,
      "ProjectFK": 1,
      "Project": null,
      "NotePackets": null
    },
    {
      "PacketID": 18,
      "Title": "Inverse of matrices and its properties",
      "Resume": null,
      "Selected": false,
      "Editable": false,
      "ParentID": 10,
      "ProjectFK": 1,
      "Project": null,
      "NotePackets": null
    },
    {
      "PacketID": 19,
      "Title": "Solving linear equations using matrix inverse",
      "Resume": null,
      "Selected": false,
      "Editable": false,
      "ParentID": 10,
      "ProjectFK": 1,
      "Project": null,
      "NotePackets": null
    },
    {
      "PacketID": 20,
      "Title": "Determinants and their properties",
      "Resume": null,
      "Selected": false,
      "Editable": false,
      "ParentID": 10,
      "ProjectFK": 1,
      "Project": null,
      "NotePackets": null
    },
    {
      "PacketID": 21,
      "Title": "LU decomposition",
      "Resume": null,
      "Selected": false,
      "Editable": false,
      "ParentID": 11,
      "ProjectFK": 1,
      "Project": null,
      "NotePackets": null
    },
    {
      "PacketID": 22,
      "Title": "QR decomposition",
      "Resume": null,
      "Selected": false,
      "Editable": false,
      "ParentID": 11,
      "ProjectFK": 1,
      "Project": null,
      "NotePackets": null
    },
    {
      "PacketID": 23,
      "Title": "Cholesky decomposition",
      "Resume": null,
      "Selected": false,
      "Editable": false,
      "ParentID": 11,
      "ProjectFK": 1,
      "Project": null,
      "NotePackets": null
    },
    {
      "PacketID": 24,
      "Title": "Singular value decomposition (SVD)",
      "Resume": null,
      "Selected": false,
      "Editable": false,
      "ParentID": 11,
      "ProjectFK": 1,
      "Project": null,
      "NotePackets": null
    },
    {
      "PacketID": 25,
      "Title": "Eigenvalue and eigenvector decomposition",
      "Resume": null,
      "Selected": false,
      "Editable": false,
      "ParentID": 11,
      "ProjectFK": 1,
      "Project": null,
      "NotePackets": null
    },
    {
      "PacketID": 26,
      "Title": "Linear regression and least squares problems",
      "Resume": null,
      "Selected": false,
      "Editable": false,
      "ParentID": 12,
      "ProjectFK": 1,
      "Project": null,
      "NotePackets": null
    },
    {
      "PacketID": 27,
      "Title": "Markov chains and random walks",
      "Resume": null,
      "Selected": false,
      "Editable": false,
      "ParentID": 12,
      "ProjectFK": 1,
      "Project": null,
      "NotePackets": null
    },
    {
      "PacketID": 28,
      "Title": "Image processing and computer graphics",
      "Resume": null,
      "Selected": false,
      "Editable": false,
      "ParentID": 12,
      "ProjectFK": 1,
      "Project": null,
      "NotePackets": null
    },
    {
      "PacketID": 29,
      "Title": "Network analysis and graph theory",
      "Resume": null,
      "Selected": false,
      "Editable": false,
      "ParentID": 12,
      "ProjectFK": 1,
      "Project": null,
      "NotePackets": null
    },
    {
      "PacketID": 30,
      "Title": "Data compression and dimensionality reduction",
      "Resume": null,
      "Selected": false,
      "Editable": false,
      "ParentID": 12,
      "ProjectFK": 1,
      "Project": null,
      "NotePackets": null
    },
    {
      "PacketID": 31,
      "Title": "Basic Vector Operations",
      "Resume": null,
      "Selected": false,
      "Editable": false,
      "ParentID": 5,
      "ProjectFK": 1,
      "Project": null,
      "NotePackets": null
    },
    {
      "PacketID": 32,
      "Title": "Vector Spaces",
      "Resume": null,
      "Selected": false,
      "Editable": false,
      "ParentID": 5,
      "ProjectFK": 1,
      "Project": null,
      "NotePackets": null
    },
    {
      "PacketID": 33,
      "Title": "Linear Transformations",
      "Resume": null,
      "Selected": false,
      "Editable": false,
      "ParentID": 5,
      "ProjectFK": 1,
      "Project": null,
      "NotePackets": null
    },
    {
      "PacketID": 34,
      "Title": "Orthogonality",
      "Resume": null,
      "Selected": false,
      "Editable": false,
      "ParentID": 5,
      "ProjectFK": 1,
      "Project": null,
      "NotePackets": null
    },
    {
      "PacketID": 35,
      "Title": "Scalar multiplication",
      "Resume": null,
      "Selected": false,
      "Editable": false,
      "ParentID": 31,
      "ProjectFK": 1,
      "Project": null,
      "NotePackets": null
    },
    {
      "PacketID": 36,
      "Title": "Dot product",
      "Resume": null,
      "Selected": false,
      "Editable": false,
      "ParentID": 31,
      "ProjectFK": 1,
      "Project": null,
      "NotePackets": null
    },
    {
      "PacketID": 37,
      "Title": "Cross product",
      "Resume": null,
      "Selected": false,
      "Editable": false,
      "ParentID": 31,
      "ProjectFK": 1,
      "Project": null,
      "NotePackets": null
    },
    {
      "PacketID": 38,
      "Title": "Basis vectors",
      "Resume": null,
      "Selected": false,
      "Editable": false,
      "ParentID": 32,
      "ProjectFK": 1,
      "Project": null,
      "NotePackets": null
    },
    {
      "PacketID": 39,
      "Title": "Spanning set",
      "Resume": null,
      "Selected": false,
      "Editable": false,
      "ParentID": 32,
      "ProjectFK": 1,
      "Project": null,
      "NotePackets": null
    },
    {
      "PacketID": 40,
      "Title": "Linear independence",
      "Resume": null,
      "Selected": false,
      "Editable": false,
      "ParentID": 32,
      "ProjectFK": 1,
      "Project": null,
      "NotePackets": null
    },
    {
      "PacketID": 41,
      "Title": "Dimension of vector space",
      "Resume": null,
      "Selected": false,
      "Editable": false,
      "ParentID": 32,
      "ProjectFK": 1,
      "Project": null,
      "NotePackets": null
    },
    {
      "PacketID": 42,
      "Title": "Linear maps",
      "Resume": null,
      "Selected": false,
      "Editable": false,
      "ParentID": 33,
      "ProjectFK": 1,
      "Project": null,
      "NotePackets": null
    },
    {
      "PacketID": 43,
      "Title": "Matrix-vector multiplication",
      "Resume": null,
      "Selected": false,
      "Editable": false,
      "ParentID": 33,
      "ProjectFK": 1,
      "Project": null,
      "NotePackets": null
    },
    {
      "PacketID": 44,
      "Title": "Image and kernel of a transformation",
      "Resume": null,
      "Selected": false,
      "Editable": false,
      "ParentID": 33,
      "ProjectFK": 1,
      "Project": null,
      "NotePackets": null
    },
    {
      "PacketID": 45,
      "Title": "Inverse of a matrix",
      "Resume": null,
      "Selected": false,
      "Editable": false,
      "ParentID": 33,
      "ProjectFK": 1,
      "Project": null,
      "NotePackets": null
    },
    {
      "PacketID": 46,
      "Title": "Orthogonal vectors",
      "Resume": null,
      "Selected": false,
      "Editable": false,
      "ParentID": 34,
      "ProjectFK": 1,
      "Project": null,
      "NotePackets": null
    },
    {
      "PacketID": 47,
      "Title": "Orthonormal vectors",
      "Resume": null,
      "Selected": false,
      "Editable": false,
      "ParentID": 34,
      "ProjectFK": 1,
      "Project": null,
      "NotePackets": null
    },
    {
      "PacketID": 48,
      "Title": "Gram-Schmidt process",
      "Resume": null,
      "Selected": false,
      "Editable": false,
      "ParentID": 34,
      "ProjectFK": 1,
      "Project": null,
      "NotePackets": null
    },
    {
      "PacketID": 49,
      "Title": "Orthogonal projection",
      "Resume": null,
      "Selected": false,
      "Editable": false,
      "ParentID": 34,
      "ProjectFK": 1,
      "Project": null,
      "NotePackets": null
    },
    {
      "PacketID": 50,
      "Title": "Linear Combinations",
      "Resume": null,
      "Selected": false,
      "Editable": false,
      "ParentID": 6,
      "ProjectFK": 1,
      "Project": null,
      "NotePackets": null
    },
    {
      "PacketID": 51,
      "Title": "Span",
      "Resume": null,
      "Selected": false,
      "Editable": false,
      "ParentID": 6,
      "ProjectFK": 1,
      "Project": null,
      "NotePackets": null
    },
    {
      "PacketID": 52,
      "Title": "Definition of linear combinations",
      "Resume": null,
      "Selected": false,
      "Editable": false,
      "ParentID": 50,
      "ProjectFK": 1,
      "Project": null,
      "NotePackets": null
    },
    {
      "PacketID": 53,
      "Title": "Linear combinations of vectors",
      "Resume": null,
      "Selected": false,
      "Editable": false,
      "ParentID": 50,
      "ProjectFK": 1,
      "Project": null,
      "NotePackets": null
    },
    {
      "PacketID": 54,
      "Title": "Linearly dependent and independent vectors",
      "Resume": null,
      "Selected": false,
      "Editable": false,
      "ParentID": 50,
      "ProjectFK": 1,
      "Project": null,
      "NotePackets": null
    },
    {
      "PacketID": 55,
      "Title": "Basis vectors and span",
      "Resume": null,
      "Selected": false,
      "Editable": false,
      "ParentID": 50,
      "ProjectFK": 1,
      "Project": null,
      "NotePackets": null
    },
    {
      "PacketID": 56,
      "Title": "Coefficient vectors and systems of linear equations",
      "Resume": null,
      "Selected": false,
      "Editable": false,
      "ParentID": 50,
      "ProjectFK": 1,
      "Project": null,
      "NotePackets": null
    },
    {
      "PacketID": 57,
      "Title": "Definition of span",
      "Resume": null,
      "Selected": false,
      "Editable": false,
      "ParentID": 51,
      "ProjectFK": 1,
      "Project": null,
      "NotePackets": null
    },
    {
      "PacketID": 58,
      "Title": "Spanning sets and minimal spanning sets",
      "Resume": null,
      "Selected": false,
      "Editable": false,
      "ParentID": 51,
      "ProjectFK": 1,
      "Project": null,
      "NotePackets": null
    },
    {
      "PacketID": 59,
      "Title": "Basis and dimension",
      "Resume": null,
      "Selected": false,
      "Editable": false,
      "ParentID": 51,
      "ProjectFK": 1,
      "Project": null,
      "NotePackets": null
    },
    {
      "PacketID": 60,
      "Title": "Linear transformations and image and kernel spaces",
      "Resume": null,
      "Selected": false,
      "Editable": false,
      "ParentID": 51,
      "ProjectFK": 1,
      "Project": null,
      "NotePackets": null
    },
    {
      "PacketID": 61,
      "Title": "Orthogonalization and Gram-Schmidt process",
      "Resume": null,
      "Selected": false,
      "Editable": false,
      "ParentID": 51,
      "ProjectFK": 1,
      "Project": null,
      "NotePackets": null
    },
    {
      "PacketID": 62,
      "Title": "Basics",
      "Resume": null,
      "Selected": false,
      "Editable": false,
      "ParentID": 7,
      "ProjectFK": 1,
      "Project": null,
      "NotePackets": null
    },
    {
      "PacketID": 63,
      "Title": "Rank",
      "Resume": null,
      "Selected": false,
      "Editable": false,
      "ParentID": 7,
      "ProjectFK": 1,
      "Project": null,
      "NotePackets": null
    },
    {
      "PacketID": 64,
      "Title": "Linear transformations",
      "Resume": null,
      "Selected": false,
      "Editable": false,
      "ParentID": 7,
      "ProjectFK": 1,
      "Project": null,
      "NotePackets": null
    },
    {
      "PacketID": 66,
      "Title": "Definition of linear independence",
      "Resume": null,
      "Selected": false,
      "Editable": false,
      "ParentID": 62,
      "ProjectFK": 1,
      "Project": null,
      "NotePackets": null
    },
    {
      "PacketID": 67,
      "Title": "Definition of linear dependence",
      "Resume": null,
      "Selected": false,
      "Editable": false,
      "ParentID": 62,
      "ProjectFK": 1,
      "Project": null,
      "NotePackets": null
    },
    {
      "PacketID": 68,
      "Title": "Definition of a span of vectors",
      "Resume": null,
      "Selected": false,
      "Editable": false,
      "ParentID": 62,
      "ProjectFK": 1,
      "Project": null,
      "NotePackets": null
    },
    {
      "PacketID": 69,
      "Title": "Definition of a basis of a vector space",
      "Resume": null,
      "Selected": false,
      "Editable": false,
      "ParentID": 62,
      "ProjectFK": 1,
      "Project": null,
      "NotePackets": null
    },
    {
      "PacketID": 70,
      "Title": "Definition of a subspace",
      "Resume": null,
      "Selected": false,
      "Editable": false,
      "ParentID": 62,
      "ProjectFK": 1,
      "Project": null,
      "NotePackets": null
    },
    {
      "PacketID": 71,
      "Title": "Definition of rank",
      "Resume": null,
      "Selected": false,
      "Editable": false,
      "ParentID": 63,
      "ProjectFK": 1,
      "Project": null,
      "NotePackets": null
    },
    {
      "PacketID": 72,
      "Title": "Calculation of the rank of a matrix",
      "Resume": null,
      "Selected": false,
      "Editable": false,
      "ParentID": 63,
      "ProjectFK": 1,
      "Project": null,
      "NotePackets": null
    },
    {
      "PacketID": 73,
      "Title": "The rank-nullity theorem",
      "Resume": null,
      "Selected": false,
      "Editable": false,
      "ParentID": 63,
      "ProjectFK": 1,
      "Project": null,
      "NotePackets": null
    },
    {
      "PacketID": 74,
      "Title": "Using the rank to determine linear independence or dependence",
      "Resume": null,
      "Selected": false,
      "Editable": false,
      "ParentID": 63,
      "ProjectFK": 1,
      "Project": null,
      "NotePackets": null
    },
    {
      "PacketID": 75,
      "Title": "Definition of a linear transformation",
      "Resume": null,
      "Selected": false,
      "Editable": false,
      "ParentID": 64,
      "ProjectFK": 1,
      "Project": null,
      "NotePackets": null
    },
    {
      "PacketID": 76,
      "Title": "The relationship between the rank of a matrix and the rank of its corresponding linear transformation",
      "Resume": null,
      "Selected": false,
      "Editable": false,
      "ParentID": 64,
      "ProjectFK": 1,
      "Project": null,
      "NotePackets": null
    },
    {
      "PacketID": 77,
      "Title": "The rank-nullity theorem for linear transformations",
      "Resume": null,
      "Selected": false,
      "Editable": false,
      "ParentID": 64,
      "ProjectFK": 1,
      "Project": null,
      "NotePackets": null
    },
    {
      "PacketID": 78,
      "Title": "Using rank to determine invertibility of a linear transformation",
      "Resume": null,
      "Selected": false,
      "Editable": false,
      "ParentID": 64,
      "ProjectFK": 1,
      "Project": null,
      "NotePackets": null
    },
    {
      "PacketID": 79,
      "Title": "Basic concepts",
      "Resume": null,
      "Selected": false,
      "Editable": false,
      "ParentID": 8,
      "ProjectFK": 1,
      "Project": null,
      "NotePackets": null
    },
    {
      "PacketID": 80,
      "Title": "Techniques for solving systems of linear equations",
      "Resume": null,
      "Selected": false,
      "Editable": false,
      "ParentID": 8,
      "ProjectFK": 1,
      "Project": null,
      "NotePackets": null
    },
    {
      "PacketID": 81,
      "Title": "Advanced topics",
      "Resume": null,
      "Selected": false,
      "Editable": false,
      "ParentID": 8,
      "ProjectFK": 1,
      "Project": null,
      "NotePackets": null
    },
    {
      "PacketID": 82,
      "Title": "System of linear equations",
      "Resume": null,
      "Selected": false,
      "Editable": false,
      "ParentID": 79,
      "ProjectFK": 1,
      "Project": null,
      "NotePackets": null
    },
    {
      "PacketID": 83,
      "Title": "Solution sets",
      "Resume": null,
      "Selected": false,
      "Editable": false,
      "ParentID": 79,
      "ProjectFK": 1,
      "Project": null,
      "NotePackets": null
    },
    {
      "PacketID": 84,
      "Title": "Row operations and row echelon form",
      "Resume": null,
      "Selected": false,
      "Editable": false,
      "ParentID": 79,
      "ProjectFK": 1,
      "Project": null,
      "NotePackets": null
    },
    {
      "PacketID": 85,
      "Title": "Reduced row echelon form",
      "Resume": null,
      "Selected": false,
      "Editable": false,
      "ParentID": 79,
      "ProjectFK": 1,
      "Project": null,
      "NotePackets": null
    },
    {
      "PacketID": 86,
      "Title": "Homogeneous and non-homogeneous systems",
      "Resume": null,
      "Selected": false,
      "Editable": false,
      "ParentID": 79,
      "ProjectFK": 1,
      "Project": null,
      "NotePackets": null
    },
    {
      "PacketID": 87,
      "Title": "Rank and nullity of a matrix",
      "Resume": null,
      "Selected": false,
      "Editable": false,
      "ParentID": 79,
      "ProjectFK": 1,
      "Project": null,
      "NotePackets": null
    },
    {
      "PacketID": 88,
      "Title": "Gaussian elimination",
      "Resume": null,
      "Selected": false,
      "Editable": false,
      "ParentID": 80,
      "ProjectFK": 1,
      "Project": null,
      "NotePackets": null
    },
    {
      "PacketID": 89,
      "Title": "LU decomposition",
      "Resume": null,
      "Selected": false,
      "Editable": false,
      "ParentID": 80,
      "ProjectFK": 1,
      "Project": null,
      "NotePackets": null
    },
    {
      "PacketID": 90,
      "Title": "Gauss-Jordan elimination",
      "Resume": null,
      "Selected": false,
      "Editable": false,
      "ParentID": 80,
      "ProjectFK": 1,
      "Project": null,
      "NotePackets": null
    },
    {
      "PacketID": 91,
      "Title": "Cramer\u0027s rule",
      "Resume": null,
      "Selected": false,
      "Editable": false,
      "ParentID": 80,
      "ProjectFK": 1,
      "Project": null,
      "NotePackets": null
    },
    {
      "PacketID": 92,
      "Title": "Inverse matrix method",
      "Resume": null,
      "Selected": false,
      "Editable": false,
      "ParentID": 80,
      "ProjectFK": 1,
      "Project": null,
      "NotePackets": null
    },
    {
      "PacketID": 93,
      "Title": "Singular and non-singular matrices",
      "Resume": null,
      "Selected": false,
      "Editable": false,
      "ParentID": 81,
      "ProjectFK": 1,
      "Project": null,
      "NotePackets": null
    },
    {
      "PacketID": 94,
      "Title": "QR decomposition",
      "Resume": null,
      "Selected": false,
      "Editable": false,
      "ParentID": 81,
      "ProjectFK": 1,
      "Project": null,
      "NotePackets": null
    },
    {
      "PacketID": 95,
      "Title": "SVD and eigenvalue decomposition",
      "Resume": null,
      "Selected": false,
      "Editable": false,
      "ParentID": 81,
      "ProjectFK": 1,
      "Project": null,
      "NotePackets": null
    },
    {
      "PacketID": 96,
      "Title": "Systems of differential equations",
      "Resume": null,
      "Selected": false,
      "Editable": false,
      "ParentID": 81,
      "ProjectFK": 1,
      "Project": null,
      "NotePackets": null
    },
    {
      "PacketID": 97,
      "Title": "Nonlinear systems of equations",
      "Resume": null,
      "Selected": false,
      "Editable": false,
      "ParentID": 81,
      "ProjectFK": 1,
      "Project": null,
      "NotePackets": null
    },
    {
      "PacketID": 105,
      "Title": "Eigenvalues and eigenvectors",
      "Resume": null,
      "Selected": false,
      "Editable": false,
      "ParentID": 3,
      "ProjectFK": 1,
      "Project": null,
      "NotePackets": null
    },
    {
      "PacketID": 106,
      "Title": "Singular value decomposition",
      "Resume": null,
      "Selected": false,
      "Editable": false,
      "ParentID": 3,
      "ProjectFK": 1,
      "Project": null,
      "NotePackets": null
    },
    {
      "PacketID": 107,
      "Title": "Orthogonalization",
      "Resume": null,
      "Selected": false,
      "Editable": false,
      "ParentID": 3,
      "ProjectFK": 1,
      "Project": null,
      "NotePackets": null
    },
    {
      "PacketID": 110,
      "Title": "Basic concepts",
      "Resume": null,
      "Selected": false,
      "Editable": false,
      "ParentID": 105,
      "ProjectFK": 1,
      "Project": null,
      "NotePackets": null
    },
    {
      "PacketID": 111,
      "Title": "Techniques for computing eigenvalues and eigenvectors",
      "Resume": null,
      "Selected": false,
      "Editable": false,
      "ParentID": 105,
      "ProjectFK": 1,
      "Project": null,
      "NotePackets": null
    },
    {
      "PacketID": 112,
      "Title": "Eigenvalues and eigenvectors of a matrix",
      "Resume": null,
      "Selected": false,
      "Editable": false,
      "ParentID": 110,
      "ProjectFK": 1,
      "Project": null,
      "NotePackets": null
    },
    {
      "PacketID": 113,
      "Title": "Eigenspace and eigendecomposition",
      "Resume": null,
      "Selected": false,
      "Editable": false,
      "ParentID": 110,
      "ProjectFK": 1,
      "Project": null,
      "NotePackets": null
    },
    {
      "PacketID": 114,
      "Title": "Characteristic polynomial and characteristic equation",
      "Resume": null,
      "Selected": false,
      "Editable": false,
      "ParentID": 110,
      "ProjectFK": 1,
      "Project": null,
      "NotePackets": null
    },
    {
      "PacketID": 115,
      "Title": "Diagonalization of a matrix",
      "Resume": null,
      "Selected": false,
      "Editable": false,
      "ParentID": 110,
      "ProjectFK": 1,
      "Project": null,
      "NotePackets": null
    },
    {
      "PacketID": 116,
      "Title": "Similarity transformations",
      "Resume": null,
      "Selected": false,
      "Editable": false,
      "ParentID": 110,
      "ProjectFK": 1,
      "Project": null,
      "NotePackets": null
    },
    {
      "PacketID": 117,
      "Title": "Power method",
      "Resume": null,
      "Selected": false,
      "Editable": false,
      "ParentID": 111,
      "ProjectFK": 1,
      "Project": null,
      "NotePackets": null
    },
    {
      "PacketID": 118,
      "Title": "Inverse iteration",
      "Resume": null,
      "Selected": false,
      "Editable": false,
      "ParentID": 111,
      "ProjectFK": 1,
      "Project": null,
      "NotePackets": null
    },
    {
      "PacketID": 119,
      "Title": "QR algorithm",
      "Resume": null,
      "Selected": false,
      "Editable": false,
      "ParentID": 111,
      "ProjectFK": 1,
      "Project": null,
      "NotePackets": null
    },
    {
      "PacketID": 120,
      "Title": "Jacobi method",
      "Resume": null,
      "Selected": false,
      "Editable": false,
      "ParentID": 111,
      "ProjectFK": 1,
      "Project": null,
      "NotePackets": null
    },
    {
      "PacketID": 121,
      "Title": "Lanczos method",
      "Resume": null,
      "Selected": false,
      "Editable": false,
      "ParentID": 111,
      "ProjectFK": 1,
      "Project": null,
      "NotePackets": null
    },
    {
      "PacketID": 122,
      "Title": "Basic concepts",
      "Resume": null,
      "Selected": false,
      "Editable": false,
      "ParentID": 106,
      "ProjectFK": 1,
      "Project": null,
      "NotePackets": null
    },
    {
      "PacketID": 123,
      "Title": "Applications of SVD in data science",
      "Resume": null,
      "Selected": false,
      "Editable": false,
      "ParentID": 106,
      "ProjectFK": 1,
      "Project": null,
      "NotePackets": null
    },
    {
      "PacketID": 124,
      "Title": "Techniques for computing SVD",
      "Resume": null,
      "Selected": false,
      "Editable": false,
      "ParentID": 106,
      "ProjectFK": 1,
      "Project": null,
      "NotePackets": null
    },
    {
      "PacketID": 125,
      "Title": "Advanced topics",
      "Resume": null,
      "Selected": false,
      "Editable": false,
      "ParentID": 106,
      "ProjectFK": 1,
      "Project": null,
      "NotePackets": null
    },
    {
      "PacketID": 126,
      "Title": "Matrix factorization",
      "Resume": null,
      "Selected": false,
      "Editable": false,
      "ParentID": 122,
      "ProjectFK": 1,
      "Project": null,
      "NotePackets": null
    },
    {
      "PacketID": 127,
      "Title": "Orthogonal matrices and unitary matrices",
      "Resume": null,
      "Selected": false,
      "Editable": false,
      "ParentID": 122,
      "ProjectFK": 1,
      "Project": null,
      "NotePackets": null
    },
    {
      "PacketID": 128,
      "Title": "Singular values and singular vectors",
      "Resume": null,
      "Selected": false,
      "Editable": false,
      "ParentID": 122,
      "ProjectFK": 1,
      "Project": null,
      "NotePackets": null
    },
    {
      "PacketID": 129,
      "Title": "Truncated SVD",
      "Resume": null,
      "Selected": false,
      "Editable": false,
      "ParentID": 122,
      "ProjectFK": 1,
      "Project": null,
      "NotePackets": null
    },
    {
      "PacketID": 130,
      "Title": "Principal component analysis (PCA)",
      "Resume": null,
      "Selected": false,
      "Editable": false,
      "ParentID": 123,
      "ProjectFK": 1,
      "Project": null,
      "NotePackets": null
    },
    {
      "PacketID": 131,
      "Title": "Image compression and reconstruction",
      "Resume": null,
      "Selected": false,
      "Editable": false,
      "ParentID": 123,
      "ProjectFK": 1,
      "Project": null,
      "NotePackets": null
    },
    {
      "PacketID": 132,
      "Title": "Collaborative filtering for recommendation systems",
      "Resume": null,
      "Selected": false,
      "Editable": false,
      "ParentID": 123,
      "ProjectFK": 1,
      "Project": null,
      "NotePackets": null
    },
    {
      "PacketID": 133,
      "Title": "Text mining and natural language processing",
      "Resume": null,
      "Selected": false,
      "Editable": false,
      "ParentID": 123,
      "ProjectFK": 1,
      "Project": null,
      "NotePackets": null
    },
    {
      "PacketID": 134,
      "Title": "Clustering and classification of data",
      "Resume": null,
      "Selected": false,
      "Editable": false,
      "ParentID": 123,
      "ProjectFK": 1,
      "Project": null,
      "NotePackets": null
    },
    {
      "PacketID": 135,
      "Title": "Power iteration method",
      "Resume": null,
      "Selected": false,
      "Editable": false,
      "ParentID": 124,
      "ProjectFK": 1,
      "Project": null,
      "NotePackets": null
    },
    {
      "PacketID": 136,
      "Title": "Jacobi method",
      "Resume": null,
      "Selected": false,
      "Editable": false,
      "ParentID": 124,
      "ProjectFK": 1,
      "Project": null,
      "NotePackets": null
    },
    {
      "PacketID": 137,
      "Title": "Lanczos algorithm",
      "Resume": null,
      "Selected": false,
      "Editable": false,
      "ParentID": 124,
      "ProjectFK": 1,
      "Project": null,
      "NotePackets": null
    },
    {
      "PacketID": 138,
      "Title": "QR algorithm",
      "Resume": null,
      "Selected": false,
      "Editable": false,
      "ParentID": 124,
      "ProjectFK": 1,
      "Project": null,
      "NotePackets": null
    },
    {
      "PacketID": 139,
      "Title": "Rank-deficient matrices and low-rank approximations",
      "Resume": null,
      "Selected": false,
      "Editable": false,
      "ParentID": 125,
      "ProjectFK": 1,
      "Project": null,
      "NotePackets": null
    },
    {
      "PacketID": 140,
      "Title": "Non-negative matrix factorization (NMF)",
      "Resume": null,
      "Selected": false,
      "Editable": false,
      "ParentID": 125,
      "ProjectFK": 1,
      "Project": null,
      "NotePackets": null
    },
    {
      "PacketID": 141,
      "Title": "Randomized SVD and fast SVD algorithms",
      "Resume": null,
      "Selected": false,
      "Editable": false,
      "ParentID": 125,
      "ProjectFK": 1,
      "Project": null,
      "NotePackets": null
    },
    {
      "PacketID": 142,
      "Title": "Applications of SVD in machine learning",
      "Resume": null,
      "Selected": false,
      "Editable": false,
      "ParentID": 125,
      "ProjectFK": 1,
      "Project": null,
      "NotePackets": null
    },
    {
      "PacketID": 143,
      "Title": "Tensor decomposition and multilinear SVD",
      "Resume": null,
      "Selected": false,
      "Editable": false,
      "ParentID": 125,
      "ProjectFK": 1,
      "Project": null,
      "NotePackets": null
    },
    {
      "PacketID": 144,
      "Title": "Basic concepts",
      "Resume": null,
      "Selected": false,
      "Editable": false,
      "ParentID": 107,
      "ProjectFK": 1,
      "Project": null,
      "NotePackets": null
    },
    {
      "PacketID": 145,
      "Title": "Techniques for orthogonalization",
      "Resume": null,
      "Selected": false,
      "Editable": false,
      "ParentID": 107,
      "ProjectFK": 1,
      "Project": null,
      "NotePackets": null
    },
    {
      "PacketID": 148,
      "Title": "Orthogonal vectors and matrices",
      "Resume": null,
      "Selected": false,
      "Editable": false,
      "ParentID": 144,
      "ProjectFK": 1,
      "Project": null,
      "NotePackets": null
    },
    {
      "PacketID": 149,
      "Title": "Orthonormal vectors and matrices",
      "Resume": null,
      "Selected": false,
      "Editable": false,
      "ParentID": 144,
      "ProjectFK": 1,
      "Project": null,
      "NotePackets": null
    },
    {
      "PacketID": 150,
      "Title": "Gram-Schmidt process",
      "Resume": null,
      "Selected": false,
      "Editable": false,
      "ParentID": 144,
      "ProjectFK": 1,
      "Project": null,
      "NotePackets": null
    },
    {
      "PacketID": 151,
      "Title": "QR decomposition",
      "Resume": null,
      "Selected": false,
      "Editable": false,
      "ParentID": 144,
      "ProjectFK": 1,
      "Project": null,
      "NotePackets": null
    },
    {
      "PacketID": 152,
      "Title": "Gram-Schmidt orthogonalization",
      "Resume": null,
      "Selected": false,
      "Editable": false,
      "ParentID": 145,
      "ProjectFK": 1,
      "Project": null,
      "NotePackets": null
    },
    {
      "PacketID": 153,
      "Title": "Householder transformation",
      "Resume": null,
      "Selected": false,
      "Editable": false,
      "ParentID": 145,
      "ProjectFK": 1,
      "Project": null,
      "NotePackets": null
    },
    {
      "PacketID": 154,
      "Title": "Givens rotation",
      "Resume": null,
      "Selected": false,
      "Editable": false,
      "ParentID": 145,
      "ProjectFK": 1,
      "Project": null,
      "NotePackets": null
    }
  ],
  "NotesCollection": [
    {
      "NotesCollectionID": 1,
      "Title": "Default Collection",
      "Selected": true,
      "Editable": false,
      "ProjectFK": 1,
      "Project": null,
      "Note": []
    }
  ]
}